linedoll/__init__.py
linedoll-0.0.1a0.dist-info/LICENSE
linedoll-0.0.1a0.dist-info/METADATA
linedoll-0.0.1a0.dist-info/WHEEL
linedoll-0.0.1a0.dist-info/top_level.txt
linedoll-0.0.1a0.dist-info/RECORD
